gnucash_portfolio_cli/__init__.py
gnucash_portfolio_cli/account_search.py
gnucash_portfolio_cli/aus_tax.py
gnucash_portfolio_cli/favourite-accounts.py
gnucash_portfolio_cli/favourite_accounts.py
gnucash_portfolio_cli/gpcli.py
gnucash_portfolio_cli/portfolio_value.py
gnucash_portfolio_cli/security_info.py
gnucash_portfolio_cli/security_search.py
gnucash_portfolio_cli/upcoming_scheduled_transactions.py
gnucash_portfolio_cli/web_view.py
gnucash_portfolio_cli/webview.py
gnucash_portfolio_cli-1.5.2.dist-info/LICENSE
gnucash_portfolio_cli-1.5.2.dist-info/METADATA
gnucash_portfolio_cli-1.5.2.dist-info/WHEEL
gnucash_portfolio_cli-1.5.2.dist-info/entry_points.txt
gnucash_portfolio_cli-1.5.2.dist-info/top_level.txt
gnucash_portfolio_cli-1.5.2.dist-info/RECORD
